Metadata-Version: 1.0
Name: PhySpeTree
Version: 0.3.9
Summary: One command line auto reconstruct phylogenetic tree.
Home-page: https://github.com/yangfangs/physpetools
Author: Yang Fang
Author-email: yangfangscu@gmail.com
License: UNKNOWN
Platform: UNKNOWN
